dydone/__init__.py
dydone/dycli.py
dydone/dypath.py
dydone/dypbar.py
dydone-1.1.2.dist-info/LICENSE
dydone-1.1.2.dist-info/METADATA
dydone-1.1.2.dist-info/WHEEL
dydone-1.1.2.dist-info/top_level.txt
dydone-1.1.2.dist-info/RECORD
