Metadata-Version: 2.1
Name: dydone
Version: 1.1.2
Summary: Done utilities in Python.
Author-email: Ding Yi <loongdone@gmail.com>
License: MIT License
Project-URL: Homepage, https://github.com/onedonedone/Dydone-Python
Project-URL: Repository, https://github.com/onedonedone/Dydone-Python
License-File: LICENSE
